icache.v
module icache(addr,data);
input[31:2] addr;
output[31:0] data;

reg[31:0] mem[0:1023];

assign data=mem[addr];

initial
begin
	$readmemb("inst.bin",mem);
end

endmodule

testbench/controller/controller_no_mc.v
module controller(
	_reset,clk,
	inst,iaddr,
	rw,dfunc,bfunc,
	rsel0,rsel1,rsel2,func,
	alu_op,reg_in,d_in,
	dout,din
);
input _reset,clk;
input [31:0] inst,din;
output [31:2] iaddr;
output [31:0] dout;
output rw;
output [2:0] dfunc;
output [1:0] bfunc;
output [4:0] rsel0,rsel1,rsel2;
output [5:0] func;
output alu_op,reg_in,d_in;

reg [31:2] iaddr;
reg [31:0] dout;
reg rw;
reg [2:0] dfunc;
reg [1:0] bfunc;
reg [4:0] rsel0,rsel1,rsel2;
reg [5:0] func;
reg alu_op,reg_in,d_in;

wire [5:0] opcode;
wire [4:0] rs,rt,rd;
wire [4:0] shamt;
wire [5:0] funct;
wire signed [15:0] imme;
wire [25:0] offset;

initial
begin
	$readmemh("microcode.hex",opcode_mc);
	$readmemh("microcode.hex",special_mc);
end

always@(_reset)
begin
	if(~_reset)
	begin
		iaddr=30'h3fffffff;
		{dout,rw,dfunc,bfunc,rsel0,rsel1,rsel2,func,alu_op,reg_in,d_in,j_mode}=0;
	end
end

always@(posedge clk)
begin
	case(j_mode)
	0:iaddr=iaddr+1;
	1:iaddr=iaddr+(din[0]?imme:1);
	2:iaddr={iaddr[31:28],offset};
	3:iaddr=din[31:2];
	endcase
end

assign {opcode,rs,rt,rd,shamt,funct}=inst;
assign imme=inst[15:0];
assign offset=inst[25:0];

reg[63:0] opcode_mc[0:63];
reg[63:0] special_mc[0:63];

reg[1:0] j_mode;

wire special,regimm,j,jal,beq,bne,blez,bgtz,
addi,addiu,slti,sltiu,andi,ori,xori,lui,
cop0,cop1,r1,cop1x,r2,r3,r4,r5,
r6,r7,r8,r9,special2,r10,r11,r12,
lb,lh,lwl,lw,lbu,lhu,lwr,r13,
sb,sh,swl,sw,r14,r15,swr,cache,
ll,lwc1,r16,perf,r17,ldc1,r18,r19,
sc,swc1,r20,r21,r22,sdc1,r23,r24;

assign {special,regimm,j,jal,beq,bne,blez,bgtz,addi,addiu,slti,sltiu,andi,ori,xori,lui,cop0,cop1,r1,cop1x,r2,r3,r4,r5,r6,r7,r8,r9,special2,r10,r11,r12,lb,lh,lwl,lw,lbu,lhu,lwr,r13,sb,sh,swl,sw,r14,r15,swr,cache,ll,lwc1,r16,perf,r17,ldc1,r18,r19,sc,swc1,r20,r21,r22,sdc1,r23,r24}=opcode_mc[opcode];

wire sll,movci,srl,sra,sllv,r25,srlv,srav,
jr,jalr,movz,movn,syscall,break,r26,sync,
mfhi,mthi,mflo,mtlo,r27,r28,r29,r30,
mult,multu,div,divu,r31,r32,r33,r34,
add,addu,sub,subu,_and,_or,_xor,_nor,
r35,r36,slt,sltu,r37,r38,r39,r40,
tge,tgeu,tlt,tltu,teq,r41,tne,r42,
r43,r44,r45,r46,r47,r48,r49,r50;

assign {sll,movci,srl,sra,sllv,r25,srlv,srav,jr,jalr,movz,movn,syscall,break,r26,sync,mfhi,mthi,mflo,mtlo,r27,r28,r29,r30,mult,multu,div,divu,r31,r32,r33,r34,add,addu,sub,subu,_and,_or,_xor,_nor,r35,r36,slt,sltu,r37,r38,r39,r40,tge,tgeu,tlt,tltu,teq,r41,tne,r42,r43,r44,r45,r46,r47,r48,r49,r50}=(special?special_mc[funct]:0);

always@(*)
begin
	{dout,rw,dfunc,bfunc,rsel0,rsel1,rsel2,func,alu_op,reg_in,d_in,j_mode}=0;

	if(add||addu||sub||subu||_and||_nor||_or||sllv||slt||sltu||srav||srlv||_xor||div||divu||mult||multu||mfhi||mflo||mthi||mtlo||movn||movz||jalr||jr)
	begin
		rsel0=rs;
		rsel1=rt;
		rsel2=rd;
		func=funct;
	end

	if(sll||sra||srl)
	begin
		alu_op=1;
		rsel0=rt;
		rsel2=rd;
		func=funct;
		dout={27'b0,shamt};
	end

	if(addi||addiu||andi||ori||slti||sltiu||xori)
	begin
		alu_op=1;
		rsel0=rs;
		rsel2=rt;
		func={2'b10,(slti||sltiu)?1'b1:1'b0,opcode[2:0]};
	end

	if(addi||addiu||slti||sltiu)
	begin
		dout=imme;
	end

	if(andi||ori||xori)
	begin
		dout=imme[15:0];
	end

	if(lb||lbu||lh||lhu||lwl||lw||lwr||lui||sb||sh||swl||sw||swr)
	begin
		dout=imme[15:0];
		rsel0=rs;
		dfunc=opcode[2:0];
		if(sb||sh||swl||sw||swr)
		begin
			rsel1=rt;
			rw=1;
		end
		else
		begin
			rsel2=rt;
			reg_in=1;
		end
	end

	if(beq||bne||blez||bgtz)
	begin
		j_mode=1;
		rsel0=rs;
		rsel1=rt;
		bfunc=opcode[1:0];
		d_in=1;
	end

	if(j||jal)
	begin
		j_mode=2;
		if(jal)
		begin
			rsel2=31;
			func='b001001;
		end
	end

	if(jalr||jr) j_mode=3;

	if(jalr||jal)
	begin
		dout={iaddr+1'b1,2'b0};
		alu_op=1;
	end
end

endmodule

testbench/controller/controller_tb.v
module controller_tb();
controller c(_reset,clk,inst,iaddr,rw,dfunc,bfunc,rsel0,rsel1,rsel2,func,alu_op,reg_in,d_in,dout,din);
icache i(_iaddr,inst);
reg _reset,clk;
reg [31:0] din;
reg [31:2] _iaddr;
wire [31:2] iaddr;
wire [31:0] dout,inst;
wire rw;
wire [2:0] dfunc;
wire [1:0] bfunc;
wire [4:0] rsel0,rsel1,rsel2;
wire [5:0] func;
wire alu_op,reg_in,d_in;

always
begin
#2
clk=~clk;
end

always@(posedge clk)
begin
_iaddr=_iaddr+1;
end

initial
begin
	clk=0;
	_iaddr=30'h3fffffff;

	_reset=0;
	#1
	_reset=1;

	@(posedge clk)
	$display("add r1,r2,r3");

	@(posedge clk)
	$display("sll 5,r2,r3");

	@(posedge clk)
	$display("addi -32761,r1,r2");

	@(posedge clk)
	$display("addi 7,r1,r2");

	@(posedge clk)
	$display("lbu r1+7,r2");

	@(posedge clk)
	$display("lui 7,r2");

	@(posedge clk)
	$display("sb r1+1,r2");

	@(posedge clk)
	$display("bne r7,r8,-9");

	#3 din=0;

	@(posedge clk)
	$display("blez r7,9");

	#3 din=1;

	@(posedge clk)
	$display("j 3fffff");

	@(posedge clk)
	$display("j 000000");

	@(posedge clk)
	$display("j 3fffff");

	@(posedge clk)
	$display("jal 000fff");

	@(posedge clk)
	$display("jalr r3,r7");

	#3 din=32'hbf800000;

	@(posedge clk)
	$display("jr r5");

	@(posedge clk);

	@(posedge clk)
	$finish();
end

always@(posedge clk)
begin
	#1
	$display("inst: %b_%d_%d_%d_%d_%b imme %d",c.opcode,c.rs,c.rt,c.rd,c.shamt,c.funct,c.imme);
	$display("reg: rs %d rt %d rd %d",rsel0,rsel1,rsel2);
	$display("func: a %b b %b d %b",func,bfunc,dfunc);
	$display("mux: alu_op %b reg_in %b d_in %b",alu_op,reg_in,d_in);
	$display("rw: %b",rw);
	$display("iaddr: %h",{iaddr,2'b0});
	$display("j_mode: %h din: %h",c.j_mode,c.din);
	$display("dout: %h",dout);
	$display("");
end

endmodule

testbench/controller/test.vcd
$date
	Sat Dec  6 01:03:44 2014
$end
$version
	Icarus Verilog
$end
$timescale
	1s
$end
$scope module controller_tb $end
$var reg 1 ! clk $end
$upscope $end
$scope module controller_tb $end
$var wire 32 " inst [31:0] $end
$upscope $end
$scope module controller_tb $end
$var wire 30 # iaddr [31:2] $end
$upscope $end
$scope module controller_tb $end
$var reg 32 $ din [31:0] $end
$upscope $end
$scope module controller_tb $end
$var wire 32 % dout [31:0] $end
$upscope $end
$enddefinitions $end
#0
$dumpvars
b0 %
bx $
b111111111111111111111111111111 #
bx "
0!
$end
#2
b0 #
b1000100001100000100000 "
1!
#4
0!
#6
b101 %
b1 #
b100001100101000000 "
1!
#8
0!
#10
b11111111111111111000000000000111 %
b10 #
b100000001000101000000000000111 "
1!
#12
0!
#14
b1 %
b11 #
b100000001000100000000000000001 "
1!
#16
0!
#18
b111 %
b100 #
b10010000001000100000000000000111 "
1!
#20
0!
#22
b101 #
b111100000000100000000000000111 "
1!
#24
0!
#26
b1 %
b110 #
b10100000001000100000000000000001 "
1!
#28
0!
#30
b1111111111110111 %
b111 #
b10100111010001111111111110111 "
1!
#32
0!
#33
b0 $
#34
b1000 #
b11000111000000000000000001001 "
1!
#36
0!
#37
b1 $
#38
b10001 #
b1011111111111111111111111111 "
1!
#40
0!
#42
b11111111111111111111111111 #
b1000000000000000000000000000 "
1!
#44
0!
#46
b0 #
b1011111111111111111111111111 "
1!
#48
0!
#50
b11111111111111111111111111 #
b100 %
b1100000000000011111111111111 "
1!
#52
0!
#54
b11111111111111 #
b10000000000000000000000000000 %
b11000000011100000001001 "
1!
#56
0!
#57
b10111111100000000000000000000000 $
#58
b101111111000000000000000000000 #
b101000000000000000001000 "
1!
#60
0!
#62
bx "
1!
#64
0!
#66
b101111111000000000000000000001 #
1!
